opensarlab/__init__.py
opensarlab/auth/__init__.py
opensarlab/auth/encryptedjwt.py
opensarlab_backend-1.0.4.dist-info/METADATA
opensarlab_backend-1.0.4.dist-info/WHEEL
opensarlab_backend-1.0.4.dist-info/top_level.txt
opensarlab_backend-1.0.4.dist-info/RECORD
