Metadata-Version: 2.1
Name: opensarlab-backend
Version: 1.0.4
Summary: Backend python modules for OpenSARLab
Home-page: https://github.com/ASFOpenSARlab/opensarlab-backend
Author: Alaska Satellite Facility OpenSARLab Team
Author-email: uaf-jupyterhub-asf@alaska.edu
License: BSD 3-Clause
Classifier: Development Status :: 5 - Production/Stable
Classifier: Intended Audience :: Science/Research
Classifier: Intended Audience :: Developers
Classifier: License :: OSI Approved :: BSD License
Classifier: Operating System :: POSIX :: Linux
Classifier: Programming Language :: Python :: 3.9
Requires-Dist: cryptography
Requires-Dist: pyjwt
